pdf2pdfa/__init__.py
pdf2pdfa/cli.py
pdf2pdfa/converter.py
pdf2pdfa/fonts.py
pdf2pdfa/icc.py
pdf2pdfa/metadata.py
pdf2pdfa/data/sRGB.icc.b64
pdf2pdfa-0.1.0.dist-info/licenses/LICENSE
pdf2pdfa-0.1.0.dist-info/METADATA
pdf2pdfa-0.1.0.dist-info/WHEEL
pdf2pdfa-0.1.0.dist-info/entry_points.txt
pdf2pdfa-0.1.0.dist-info/top_level.txt
pdf2pdfa-0.1.0.dist-info/RECORD
