Metadata-Version: 2.4
Name: pdf2pdfa
Version: 0.1.0
Summary: Convert arbitrary PDF files to PDF/A-1b
Author: nks1990
Author-email: nks1990 <nks1990@example.com>
License: MIT
Classifier: Programming Language :: Python :: 3
Classifier: License :: OSI Approved :: MIT License
Requires-Python: >=3.7
License-File: LICENSE
Requires-Dist: pikepdf>=4.0.0
Requires-Dist: fonttools>=4.0.0
Requires-Dist: lxml>=4.0.0
Requires-Dist: click>=7.0
Requires-Dist: importlib_resources; python_version < "3.9"
Requires-Dist: reportlab>=4.0.0
Provides-Extra: test
Requires-Dist: pytest>=6.0; extra == "test"
Dynamic: author
Dynamic: license-file
Dynamic: requires-python
